retry_module/__init__.py
retry_module/decorators.py
retry_module-0.1.0.dist-info/AUTHORS.rst
retry_module-0.1.0.dist-info/LICENSE
retry_module-0.1.0.dist-info/METADATA
retry_module-0.1.0.dist-info/WHEEL
retry_module-0.1.0.dist-info/top_level.txt
retry_module-0.1.0.dist-info/RECORD
