Metadata-Version: 2.1
Name: retry-module
Version: 0.1.0
Summary: A simple decorator for implementing retry mechanishm
Home-page: https://github.com/adityaprakash-bobby/retry_module
Author: Aditya Prakash
Author-email: adityaprakash.bobby@gmail.com
License: MIT license
Keywords: retry_module
Platform: UNKNOWN
Classifier: Development Status :: 2 - Pre-Alpha
Classifier: Intended Audience :: Developers
Classifier: License :: OSI Approved :: MIT License
Classifier: Natural Language :: English
Classifier: Programming Language :: Python :: 3
Classifier: Programming Language :: Python :: 3.5
Classifier: Programming Language :: Python :: 3.6
Classifier: Programming Language :: Python :: 3.7
Classifier: Programming Language :: Python :: 3.8
Requires-Python: >=3.5
